{
    "id": "nintendo",
    "name": "Nintendo Trivia",
    "cards": [
      {
        "red": {
          "id": "mario_games",
          "name": "Mario Games",
          "color": "red-100"
        }
      },
      {
        "green": {
          "id": "zelda_games",
          "name": "Zelda Games",
          "color": "green-100"
        }
      },
      {
        "yellow": {
          "id": "pokemon",
          "name": "Pokemon",
          "color": "yellow-100"
        }
      },
      {
        "blue": {
          "id": "nintendo_consoles",
          "name": "Nintendo Consoles",
          "color": "blue-100"
        }
      }
    ]
  }